data_ntegration/__init__.py
data_ntegration/database_writer.py
data_ntegration/receiver.py
data_ntegration-0.1.dist-info/METADATA
data_ntegration-0.1.dist-info/WHEEL
data_ntegration-0.1.dist-info/top_level.txt
data_ntegration-0.1.dist-info/RECORD
